{
  "version": "6.0",
  "nxVersion": "22.7.1",
  "pathMappings": {
    "@elev9/api-client": [
      "packages/api-client/src/index.ts"
    ],
    "@elev9/api-client/*": [
      "packages/api-client/src/*"
    ],
    "@elev9/types": [
      "packages/types/src/index.ts"
    ],
    "@elev9/types/*": [
      "packages/types/src/*"
    ]
  },
  "nxJsonPlugins": [],
  "fileMap": {
    "nonProjectFiles": [
      {
        "file": "docs/specs/training/create-training-plan/rules.md",
        "hash": "10623554897165739629"
      },
      {
        "file": "docs/specs/dashboard/get-home-dashboard/adr-links.md",
        "hash": "5611751840615688553"
      },
      {
        "file": "docs/specs/training/create-training-plan/flow.md",
        "hash": "6345836467107835074"
      },
      {
        "file": "docs/specs/training/get-my-training-plan/flow.md",
        "hash": "15738305993332842507"
      },
      {
        "file": "docs/specs/users/create-user-profile/rules.md",
        "hash": "13609736557624814227"
      },
      {
        "file": "nx.json",
        "hash": "14528439547795292007"
      },
      {
        "file": "docs/specs/auth/login-user/tests.md",
        "hash": "15451114216215816358"
      },
      {
        "file": "docs/specs/fitness/create-fitness-profile/tasks.md",
        "hash": "1071738249787814243"
      },
      {
        "file": "docs/specs/users/create-user-profile/errors.md",
        "hash": "16315950083836605211"
      },
      {
        "file": "docs/specs/_templates/use-case-template/tests.md",
        "hash": "3147484944921095604"
      },
      {
        "file": "docs/specs/training/get-my-training-plan/rules.md",
        "hash": "1685622091791354732"
      },
      {
        "file": "docs/specs/users/create-user-profile/tests.md",
        "hash": "3163301625026805001"
      },
      {
        "file": "docs/specs/fitness/create-fitness-profile/errors.md",
        "hash": "11946637933342737734"
      },
      {
        "file": "docs/specs/progress/log-workout/errors.md",
        "hash": "5384240053778805252"
      },
      {
        "file": "docs/specs/training/get-my-training-plan/README.md",
        "hash": "6317213853992629821"
      },
      {
        "file": "docs/specs/dashboard/get-home-dashboard/tests.md",
        "hash": "4597903189687012564"
      },
      {
        "file": "docs/specs/progress/log-workout/adr-links.md",
        "hash": "1694612949886093688"
      },
      {
        "file": "docs/specs/auth/validate-session/contract.md",
        "hash": "979265826390134235"
      },
      {
        "file": "docs/specs/_templates/use-case-template/adr-links.md",
        "hash": "4704094694694658005"
      },
      {
        "file": "docs/specs/dashboard/get-home-dashboard/README.md",
        "hash": "10050498668750543792"
      },
      {
        "file": "docs/architecture/architecture-overview.md",
        "hash": "3033157114179975702"
      },
      {
        "file": "docs/specs/dashboard/get-home-dashboard/contract.md",
        "hash": "2959757416660285955"
      },
      {
        "file": "docs/specs/progress/get-progress-summary/tasks.md",
        "hash": "1180092968978587026"
      },
      {
        "file": "docs/specs/progress/get-progress-summary/tests.md",
        "hash": "8774270940226331271"
      },
      {
        "file": "docs/specs/auth/validate-session/adr-links.md",
        "hash": "10033271115363736010"
      },
      {
        "file": "docs/specs/fitness/get-my-fitness-profile/README.md",
        "hash": "10390353790906088409"
      },
      {
        "file": "docs/specs/auth/login-user/contract.md",
        "hash": "11745142079576442233"
      },
      {
        "file": "docs/specs/fitness/get-my-fitness-profile/flow.md",
        "hash": "13311026335507161633"
      },
      {
        "file": "docs/specs/users/create-user-profile/contract.md",
        "hash": "2996732863824805185"
      },
      {
        "file": "tsconfig.json",
        "hash": "9926150842452991637"
      },
      {
        "file": "docs/specs/fitness/get-my-fitness-profile/tests.md",
        "hash": "9184533105550973388"
      },
      {
        "file": "docs/specs/_templates/use-case-template/errors.md",
        "hash": "2109854184917104472"
      },
      {
        "file": "docs/specs/users/create-user-profile/flow.md",
        "hash": "9398384272275452929"
      },
      {
        "file": "docs/specs/auth/register-user/tests.md",
        "hash": "6151823623607601682"
      },
      {
        "file": "docs/specs/auth/validate-session/tests.md",
        "hash": "11280551533272547985"
      },
      {
        "file": "package.json",
        "hash": "4728133022972306909"
      },
      {
        "file": "docs/specs/training/create-training-plan/README.md",
        "hash": "17819627507865932585"
      },
      {
        "file": "docs/domain/bounded-contexts.md",
        "hash": "6349993248986669016"
      },
      {
        "file": "docs/specs/progress/get-progress-summary/README.md",
        "hash": "16910527978883367347"
      },
      {
        "file": "docs/specs/training/get-my-training-plan/tests.md",
        "hash": "6250170255639205931"
      },
      {
        "file": "docs/specs/dashboard/get-home-dashboard/rules.md",
        "hash": "18019576823295118304"
      },
      {
        "file": "docs/specs/fitness/create-fitness-profile/rules.md",
        "hash": "18314890351078536857"
      },
      {
        "file": "docs/specs/auth/validate-session/errors.md",
        "hash": "1589750199321999474"
      },
      {
        "file": "docs/product/product-vision.md",
        "hash": "7078725716135318002"
      },
      {
        "file": "docs/specs/auth/validate-session/tasks.md",
        "hash": "9766603907192533014"
      },
      {
        "file": "docs/roadmap/phase-0-checklist.md",
        "hash": "4852796979435796888"
      },
      {
        "file": "docs/specs/training/get-my-training-plan/errors.md",
        "hash": "5463690078311709907"
      },
      {
        "file": "docs/architecture/monorepo.md",
        "hash": "4828320205701079477"
      },
      {
        "file": "docs/roadmap/development-roadmap.md",
        "hash": "7427627001124493091"
      },
      {
        "file": "docs/specs/progress/log-workout/contract.md",
        "hash": "12835894058566884673"
      },
      {
        "file": "docs/specs/auth/register-user/tasks.md",
        "hash": "11094367574255762260"
      },
      {
        "file": "docs/product/target-users.md",
        "hash": "14977688570329980271"
      },
      {
        "file": "docs/specs/auth/validate-session/rules.md",
        "hash": "9099002700145463281"
      },
      {
        "file": "docs/architecture/tech-stack.md",
        "hash": "4222176938945777382"
      },
      {
        "file": "docs/specs/auth/login-user/tasks.md",
        "hash": "13818839010848290964"
      },
      {
        "file": "docs/architecture/communication-flow.md",
        "hash": "6650444389043990951"
      },
      {
        "file": "docs/specs/_templates/use-case-template/flow.md",
        "hash": "14741583849215870832"
      },
      {
        "file": "packages/.gitkeep",
        "hash": "4055606894390288348"
      },
      {
        "file": "docs/specs/fitness/get-my-fitness-profile/tasks.md",
        "hash": "15990015338181937730"
      },
      {
        "file": "docs/specs/auth/validate-session/flow.md",
        "hash": "2852072280387294226"
      },
      {
        "file": "docs/specs/progress/log-workout/README.md",
        "hash": "14708928957445952028"
      },
      {
        "file": "docs/specs/auth/register-user/rules.md",
        "hash": "4037030090544047501"
      },
      {
        "file": "docs/specs/auth/login-user/errors.md",
        "hash": "1740191668207548028"
      },
      {
        "file": "docs/specs/auth/register-user/contract.md",
        "hash": "5686970546192179250"
      },
      {
        "file": "docs/specs/training/create-training-plan/tests.md",
        "hash": "13273729072630199094"
      },
      {
        "file": "docs/specs/progress/get-progress-summary/errors.md",
        "hash": "9355263486663457323"
      },
      {
        "file": "docs/product/mvp-scope.md",
        "hash": "10599866824378020453"
      },
      {
        "file": "docs/specs/_templates/use-case-template/tasks.md",
        "hash": "9139746023519656811"
      },
      {
        "file": "docs/specs/training/create-training-plan/adr-links.md",
        "hash": "14061713218491192147"
      },
      {
        "file": "package-lock.json",
        "hash": "4490168147419144809"
      },
      {
        "file": "docs/specs/auth/validate-session/README.md",
        "hash": "4907171524736782237"
      },
      {
        "file": "docs/specs/fitness/create-fitness-profile/flow.md",
        "hash": "17319399263359877251"
      },
      {
        "file": "docs/specs/progress/get-progress-summary/rules.md",
        "hash": "7862036306081078434"
      },
      {
        "file": "docs/specs/progress/log-workout/tests.md",
        "hash": "16614513170334114769"
      },
      {
        "file": ".gitignore",
        "hash": "12443555540125877725"
      },
      {
        "file": "docs/specs/_templates/use-case-template/rules.md",
        "hash": "17054007066222527815"
      },
      {
        "file": "docs/architecture/service-map.md",
        "hash": "2911549475489747100"
      },
      {
        "file": "docs/specs/fitness/create-fitness-profile/contract.md",
        "hash": "15964576940407315723"
      },
      {
        "file": "docs/specs/_templates/use-case-template/contract.md",
        "hash": "3420637009310960619"
      },
      {
        "file": "docs/specs/fitness/create-fitness-profile/adr-links.md",
        "hash": "14693512605444205543"
      },
      {
        "file": "docs/specs/auth/register-user/adr-links.md",
        "hash": "16037249859450512532"
      },
      {
        "file": "docs/specs/training/get-my-training-plan/adr-links.md",
        "hash": "4455165398757109434"
      },
      {
        "file": "docs/domain/entities.md",
        "hash": "15453014831864675818"
      },
      {
        "file": "docs/specs/_templates/use-case-template/README.md",
        "hash": "6107006494996186423"
      },
      {
        "file": "docs/specs/dashboard/get-home-dashboard/tasks.md",
        "hash": "8914904413854659807"
      },
      {
        "file": "docs/specs/progress/get-progress-summary/flow.md",
        "hash": "2208141517089013403"
      },
      {
        "file": "docs/specs/fitness/get-my-fitness-profile/contract.md",
        "hash": "8108035339079073769"
      },
      {
        "file": "docs/specs/fitness/get-my-fitness-profile/rules.md",
        "hash": "15693565267188567940"
      },
      {
        "file": "docs/specs/fitness/create-fitness-profile/tests.md",
        "hash": "431969357158861491"
      },
      {
        "file": "docs/specs/training/get-my-training-plan/contract.md",
        "hash": "12212319232633571417"
      },
      {
        "file": "docs/specs/auth/register-user/errors.md",
        "hash": "12419238126437607051"
      },
      {
        "file": "docs/specs/progress/log-workout/flow.md",
        "hash": "864229135404598263"
      },
      {
        "file": "docs/specs/training/create-training-plan/tasks.md",
        "hash": "7678279785080696243"
      },
      {
        "file": "docs/specs/auth/login-user/rules.md",
        "hash": "9217940276301961085"
      },
      {
        "file": "docs/specs/progress/get-progress-summary/adr-links.md",
        "hash": "15724586353392633178"
      },
      {
        "file": "docs/specs/users/create-user-profile/adr-links.md",
        "hash": "1785435316566469154"
      },
      {
        "file": "docs/specs/auth/login-user/README.md",
        "hash": "5666250582356872853"
      },
      {
        "file": "docs/specs/training/create-training-plan/errors.md",
        "hash": "17965378674995069746"
      },
      {
        "file": "docs/specs/fitness/create-fitness-profile/README.md",
        "hash": "9670853663603591566"
      },
      {
        "file": "docs/specs/training/create-training-plan/contract.md",
        "hash": "15889505051892160566"
      },
      {
        "file": "docs/specs/users/create-user-profile/README.md",
        "hash": "1523375627091132462"
      },
      {
        "file": "docs/specs/progress/get-progress-summary/contract.md",
        "hash": "1165926536614181822"
      },
      {
        "file": "docs/specs/progress/log-workout/tasks.md",
        "hash": "6384353748655819726"
      },
      {
        "file": "docs/specs/auth/login-user/adr-links.md",
        "hash": "17883173266455378950"
      },
      {
        "file": "docs/specs/fitness/get-my-fitness-profile/errors.md",
        "hash": "14264086094999592196"
      },
      {
        "file": "docs/domain/domain-model.md",
        "hash": "11370805417948560484"
      },
      {
        "file": "docs/specs/auth/login-user/flow.md",
        "hash": "17853220877389724112"
      },
      {
        "file": "docs/specs/auth/register-user/flow.md",
        "hash": "12400958459540467231"
      },
      {
        "file": "tsconfig.base.json",
        "hash": "10525416840300074282"
      },
      {
        "file": "docs/specs/training/get-my-training-plan/tasks.md",
        "hash": "127141225217679192"
      },
      {
        "file": "docs/specs/dashboard/get-home-dashboard/errors.md",
        "hash": "17127366863599219780"
      },
      {
        "file": "docs/specs/auth/register-user/README.md",
        "hash": "7820929969871165901"
      },
      {
        "file": "docs/specs/progress/log-workout/rules.md",
        "hash": "4352059043317372238"
      },
      {
        "file": "docs/specs/users/create-user-profile/tasks.md",
        "hash": "15319285899435909552"
      },
      {
        "file": "docs/product/product-positioning.md",
        "hash": "12410186373018747259"
      },
      {
        "file": "docs/specs/dashboard/get-home-dashboard/flow.md",
        "hash": "9149658266739134506"
      },
      {
        "file": "docs/specs/fitness/get-my-fitness-profile/adr-links.md",
        "hash": "12790474464087595121"
      }
    ],
    "projectFileMap": {
      "api-client": [
        {
          "file": "packages/api-client/package.json",
          "hash": "18171663205975414257",
          "deps": [
            "types"
          ]
        },
        {
          "file": "packages/api-client/project.json",
          "hash": "7514023994684810340"
        },
        {
          "file": "packages/api-client/src/auth-api.ts",
          "hash": "3609245476531367544"
        },
        {
          "file": "packages/api-client/src/dashboard-api.ts",
          "hash": "13401704885981006565"
        },
        {
          "file": "packages/api-client/src/fitness-api.ts",
          "hash": "2199758544260888188"
        },
        {
          "file": "packages/api-client/src/http-client.ts",
          "hash": "8769372197508038727"
        },
        {
          "file": "packages/api-client/src/index.ts",
          "hash": "16206988621089825438"
        },
        {
          "file": "packages/api-client/src/progress-api.ts",
          "hash": "1425506588193999363"
        },
        {
          "file": "packages/api-client/src/training-api.ts",
          "hash": "13270601874747877568"
        },
        {
          "file": "packages/api-client/tsconfig.json",
          "hash": "9865331543325120171"
        }
      ],
      "api": [
        {
          "file": "apps/api/jest.config.js",
          "hash": "7306831346638701644"
        },
        {
          "file": "apps/api/jest.e2e.config.js",
          "hash": "6986786169657539779"
        },
        {
          "file": "apps/api/nest-cli.json",
          "hash": "14493163345002656435"
        },
        {
          "file": "apps/api/project.json",
          "hash": "14031040025820010134"
        },
        {
          "file": "apps/api/src/app.module.ts",
          "hash": "6668827956826826875"
        },
        {
          "file": "apps/api/src/main.ts",
          "hash": "3822766588777342208"
        },
        {
          "file": "apps/api/src/modules/auth/application/use-cases/login-user/login-user.errors.ts",
          "hash": "14960892313356651110"
        },
        {
          "file": "apps/api/src/modules/auth/application/use-cases/login-user/login-user.input.ts",
          "hash": "15257236453115192728"
        },
        {
          "file": "apps/api/src/modules/auth/application/use-cases/login-user/login-user.output.ts",
          "hash": "16309013692948259243"
        },
        {
          "file": "apps/api/src/modules/auth/application/use-cases/login-user/login-user.use-case.spec.ts",
          "hash": "17775603417523996997"
        },
        {
          "file": "apps/api/src/modules/auth/application/use-cases/login-user/login-user.use-case.ts",
          "hash": "13868285306433454432"
        },
        {
          "file": "apps/api/src/modules/auth/application/use-cases/register-user/register-user.errors.ts",
          "hash": "8395648750230244366"
        },
        {
          "file": "apps/api/src/modules/auth/application/use-cases/register-user/register-user.input.ts",
          "hash": "5969766593918154027"
        },
        {
          "file": "apps/api/src/modules/auth/application/use-cases/register-user/register-user.output.ts",
          "hash": "4580927895337520143"
        },
        {
          "file": "apps/api/src/modules/auth/application/use-cases/register-user/register-user.use-case.spec.ts",
          "hash": "360330300416756984"
        },
        {
          "file": "apps/api/src/modules/auth/application/use-cases/register-user/register-user.use-case.ts",
          "hash": "5777072734324255751"
        },
        {
          "file": "apps/api/src/modules/auth/application/use-cases/validate-session/validate-session.errors.ts",
          "hash": "5320146952695247015"
        },
        {
          "file": "apps/api/src/modules/auth/application/use-cases/validate-session/validate-session.input.ts",
          "hash": "2500856431615394970"
        },
        {
          "file": "apps/api/src/modules/auth/application/use-cases/validate-session/validate-session.output.ts",
          "hash": "4007959251855229827"
        },
        {
          "file": "apps/api/src/modules/auth/application/use-cases/validate-session/validate-session.use-case.spec.ts",
          "hash": "1509815504309239897"
        },
        {
          "file": "apps/api/src/modules/auth/application/use-cases/validate-session/validate-session.use-case.ts",
          "hash": "1313820549176830450"
        },
        {
          "file": "apps/api/src/modules/auth/auth.module.ts",
          "hash": "8487160462005108150"
        },
        {
          "file": "apps/api/src/modules/auth/domain/entities/auth-user.entity.ts",
          "hash": "9637677427026269344"
        },
        {
          "file": "apps/api/src/modules/auth/domain/repositories/auth-user.repository.ts",
          "hash": "5483391855859005978"
        },
        {
          "file": "apps/api/src/modules/auth/domain/services/access-token-signer.service.ts",
          "hash": "11046861533314839420"
        },
        {
          "file": "apps/api/src/modules/auth/domain/services/access-token-verifier.service.ts",
          "hash": "1151785151567042055"
        },
        {
          "file": "apps/api/src/modules/auth/domain/services/password-hasher.service.ts",
          "hash": "17130921716598132033"
        },
        {
          "file": "apps/api/src/modules/auth/infrastructure/mongoose/auth-user.schema.ts",
          "hash": "17597845237978238535"
        },
        {
          "file": "apps/api/src/modules/auth/infrastructure/mongoose/mongoose-auth-user.repository.ts",
          "hash": "6208657973004700605"
        },
        {
          "file": "apps/api/src/modules/auth/infrastructure/security/bcrypt-password-hasher.service.ts",
          "hash": "8003979872707763109"
        },
        {
          "file": "apps/api/src/modules/auth/infrastructure/security/jwt-access-token-signer.service.ts",
          "hash": "994634602024912380"
        },
        {
          "file": "apps/api/src/modules/auth/infrastructure/security/jwt-access-token-verifier.service.ts",
          "hash": "4625329202411379161"
        },
        {
          "file": "apps/api/src/modules/auth/presentation/http/auth.controller.spec.ts",
          "hash": "12078709115504655990"
        },
        {
          "file": "apps/api/src/modules/auth/presentation/http/auth.controller.ts",
          "hash": "16893799492858998466"
        },
        {
          "file": "apps/api/src/modules/auth/presentation/http/dto/login-user.request.dto.ts",
          "hash": "6029979831827597257"
        },
        {
          "file": "apps/api/src/modules/auth/presentation/http/dto/login-user.response.dto.ts",
          "hash": "11715983069501026416"
        },
        {
          "file": "apps/api/src/modules/auth/presentation/http/dto/register-user.request.dto.ts",
          "hash": "1008398282317798569"
        },
        {
          "file": "apps/api/src/modules/auth/presentation/http/dto/register-user.response.dto.ts",
          "hash": "14218805635282974854"
        },
        {
          "file": "apps/api/src/modules/auth/presentation/http/dto/validate-session.response.dto.ts",
          "hash": "740630027092003106"
        },
        {
          "file": "apps/api/src/modules/dashboard/application/use-cases/get-home-dashboard/get-home-dashboard.errors.ts",
          "hash": "14416425012726662977"
        },
        {
          "file": "apps/api/src/modules/dashboard/application/use-cases/get-home-dashboard/get-home-dashboard.input.ts",
          "hash": "10606423775108346266"
        },
        {
          "file": "apps/api/src/modules/dashboard/application/use-cases/get-home-dashboard/get-home-dashboard.output.ts",
          "hash": "15609783095920014921"
        },
        {
          "file": "apps/api/src/modules/dashboard/application/use-cases/get-home-dashboard/get-home-dashboard.use-case.spec.ts",
          "hash": "2874040611550411562"
        },
        {
          "file": "apps/api/src/modules/dashboard/application/use-cases/get-home-dashboard/get-home-dashboard.use-case.ts",
          "hash": "9434765093054239959"
        },
        {
          "file": "apps/api/src/modules/dashboard/dashboard.module.ts",
          "hash": "6953768547195537796"
        },
        {
          "file": "apps/api/src/modules/dashboard/presentation/http/dashboard.controller.spec.ts",
          "hash": "13783716685250625758"
        },
        {
          "file": "apps/api/src/modules/dashboard/presentation/http/dashboard.controller.ts",
          "hash": "17805741155197624560"
        },
        {
          "file": "apps/api/src/modules/dashboard/presentation/http/dto/get-home-dashboard.response.dto.ts",
          "hash": "9531184903786456467"
        },
        {
          "file": "apps/api/src/modules/fitness/application/use-cases/create-fitness-profile/create-fitness-profile.errors.ts",
          "hash": "9096950399737328180"
        },
        {
          "file": "apps/api/src/modules/fitness/application/use-cases/create-fitness-profile/create-fitness-profile.input.ts",
          "hash": "14437807430110214908"
        },
        {
          "file": "apps/api/src/modules/fitness/application/use-cases/create-fitness-profile/create-fitness-profile.output.ts",
          "hash": "3143699831641547911"
        },
        {
          "file": "apps/api/src/modules/fitness/application/use-cases/create-fitness-profile/create-fitness-profile.use-case.spec.ts",
          "hash": "6890010166748093369"
        },
        {
          "file": "apps/api/src/modules/fitness/application/use-cases/create-fitness-profile/create-fitness-profile.use-case.ts",
          "hash": "3586842299627036341"
        },
        {
          "file": "apps/api/src/modules/fitness/application/use-cases/get-my-fitness-profile/get-my-fitness-profile.errors.ts",
          "hash": "116720893295598388"
        },
        {
          "file": "apps/api/src/modules/fitness/application/use-cases/get-my-fitness-profile/get-my-fitness-profile.output.ts",
          "hash": "13445436531869184156"
        },
        {
          "file": "apps/api/src/modules/fitness/application/use-cases/get-my-fitness-profile/get-my-fitness-profile.use-case.spec.ts",
          "hash": "4061093961237893784"
        },
        {
          "file": "apps/api/src/modules/fitness/application/use-cases/get-my-fitness-profile/get-my-fitness-profile.use-case.ts",
          "hash": "1440546202172064128"
        },
        {
          "file": "apps/api/src/modules/fitness/domain/entities/fitness-profile.entity.ts",
          "hash": "5560952060652197597"
        },
        {
          "file": "apps/api/src/modules/fitness/domain/repositories/fitness-profile.repository.ts",
          "hash": "17258389459040467691"
        },
        {
          "file": "apps/api/src/modules/fitness/fitness.module.ts",
          "hash": "1089947028411281083"
        },
        {
          "file": "apps/api/src/modules/fitness/infrastructure/mongoose/fitness-profile.schema.ts",
          "hash": "1844421595050782868"
        },
        {
          "file": "apps/api/src/modules/fitness/infrastructure/mongoose/mongoose-fitness-profile.repository.ts",
          "hash": "13640157750337043026"
        },
        {
          "file": "apps/api/src/modules/fitness/presentation/http/dto/create-fitness-profile.request.dto.ts",
          "hash": "14493856324805608002"
        },
        {
          "file": "apps/api/src/modules/fitness/presentation/http/dto/create-fitness-profile.response.dto.ts",
          "hash": "13315672689700677014"
        },
        {
          "file": "apps/api/src/modules/fitness/presentation/http/dto/get-my-fitness-profile.response.dto.ts",
          "hash": "5968899278353108392"
        },
        {
          "file": "apps/api/src/modules/fitness/presentation/http/fitness.controller.spec.ts",
          "hash": "17011013596589578601"
        },
        {
          "file": "apps/api/src/modules/fitness/presentation/http/fitness.controller.ts",
          "hash": "14636909125498835811"
        },
        {
          "file": "apps/api/src/modules/progress/application/use-cases/get-progress-summary/get-progress-summary.errors.ts",
          "hash": "17669916573589655469"
        },
        {
          "file": "apps/api/src/modules/progress/application/use-cases/get-progress-summary/get-progress-summary.input.ts",
          "hash": "9294059409621072384"
        },
        {
          "file": "apps/api/src/modules/progress/application/use-cases/get-progress-summary/get-progress-summary.output.ts",
          "hash": "9039223421036992278"
        },
        {
          "file": "apps/api/src/modules/progress/application/use-cases/get-progress-summary/get-progress-summary.use-case.spec.ts",
          "hash": "17286994035337841560"
        },
        {
          "file": "apps/api/src/modules/progress/application/use-cases/get-progress-summary/get-progress-summary.use-case.ts",
          "hash": "13021318038828853872"
        },
        {
          "file": "apps/api/src/modules/progress/application/use-cases/log-workout/log-workout.errors.ts",
          "hash": "12779969686721326807"
        },
        {
          "file": "apps/api/src/modules/progress/application/use-cases/log-workout/log-workout.input.ts",
          "hash": "11553292180588354677"
        },
        {
          "file": "apps/api/src/modules/progress/application/use-cases/log-workout/log-workout.output.ts",
          "hash": "8666856627644370742"
        },
        {
          "file": "apps/api/src/modules/progress/application/use-cases/log-workout/log-workout.use-case.spec.ts",
          "hash": "17290880634944175627"
        },
        {
          "file": "apps/api/src/modules/progress/application/use-cases/log-workout/log-workout.use-case.ts",
          "hash": "12811375453598404562"
        },
        {
          "file": "apps/api/src/modules/progress/domain/entities/workout-log.entity.ts",
          "hash": "7998652922325899962"
        },
        {
          "file": "apps/api/src/modules/progress/domain/repositories/workout-log.repository.ts",
          "hash": "1800902912596228020"
        },
        {
          "file": "apps/api/src/modules/progress/domain/services/clock.service.ts",
          "hash": "2963484827066900073"
        },
        {
          "file": "apps/api/src/modules/progress/infrastructure/mongoose/mongoose-workout-log.repository.ts",
          "hash": "10341188436374998549"
        },
        {
          "file": "apps/api/src/modules/progress/infrastructure/mongoose/workout-log.schema.ts",
          "hash": "14865343241750953560"
        },
        {
          "file": "apps/api/src/modules/progress/infrastructure/system-clock.service.ts",
          "hash": "17340081499801651498"
        },
        {
          "file": "apps/api/src/modules/progress/presentation/http/dto/get-progress-summary.query.dto.ts",
          "hash": "11357216601427958301"
        },
        {
          "file": "apps/api/src/modules/progress/presentation/http/dto/get-progress-summary.response.dto.ts",
          "hash": "12391296919205708263"
        },
        {
          "file": "apps/api/src/modules/progress/presentation/http/dto/log-workout.request.dto.ts",
          "hash": "3096600375183856309"
        },
        {
          "file": "apps/api/src/modules/progress/presentation/http/dto/log-workout.response.dto.ts",
          "hash": "16079965830510140110"
        },
        {
          "file": "apps/api/src/modules/progress/presentation/http/progress.controller.spec.ts",
          "hash": "6462461155273763603"
        },
        {
          "file": "apps/api/src/modules/progress/presentation/http/progress.controller.ts",
          "hash": "11215114808396483888"
        },
        {
          "file": "apps/api/src/modules/progress/progress.module.ts",
          "hash": "8516413831612336599"
        },
        {
          "file": "apps/api/src/modules/training/application/use-cases/create-training-plan/create-training-plan.errors.ts",
          "hash": "5462250078484929655"
        },
        {
          "file": "apps/api/src/modules/training/application/use-cases/create-training-plan/create-training-plan.input.ts",
          "hash": "6335184814936279557"
        },
        {
          "file": "apps/api/src/modules/training/application/use-cases/create-training-plan/create-training-plan.output.ts",
          "hash": "425996622726595204"
        },
        {
          "file": "apps/api/src/modules/training/application/use-cases/create-training-plan/create-training-plan.use-case.spec.ts",
          "hash": "4415382191004839732"
        },
        {
          "file": "apps/api/src/modules/training/application/use-cases/create-training-plan/create-training-plan.use-case.ts",
          "hash": "7946467859852292803"
        },
        {
          "file": "apps/api/src/modules/training/application/use-cases/get-my-training-plan/get-my-training-plan.errors.ts",
          "hash": "7243326679721687388"
        },
        {
          "file": "apps/api/src/modules/training/application/use-cases/get-my-training-plan/get-my-training-plan.input.ts",
          "hash": "7021312770136540321"
        },
        {
          "file": "apps/api/src/modules/training/application/use-cases/get-my-training-plan/get-my-training-plan.output.ts",
          "hash": "1621725263565659702"
        },
        {
          "file": "apps/api/src/modules/training/application/use-cases/get-my-training-plan/get-my-training-plan.use-case.spec.ts",
          "hash": "10509347463653432968"
        },
        {
          "file": "apps/api/src/modules/training/application/use-cases/get-my-training-plan/get-my-training-plan.use-case.ts",
          "hash": "4651693248820219102"
        },
        {
          "file": "apps/api/src/modules/training/domain/entities/training-plan.entity.ts",
          "hash": "12517560969136994503"
        },
        {
          "file": "apps/api/src/modules/training/domain/repositories/training-plan.repository.ts",
          "hash": "6219956035700440085"
        },
        {
          "file": "apps/api/src/modules/training/infrastructure/mongoose/mongoose-training-plan.repository.ts",
          "hash": "10707430120567829319"
        },
        {
          "file": "apps/api/src/modules/training/infrastructure/mongoose/training-plan.schema.ts",
          "hash": "926841297598890729"
        },
        {
          "file": "apps/api/src/modules/training/presentation/http/dto/create-training-plan.request.dto.ts",
          "hash": "16270505310716237710"
        },
        {
          "file": "apps/api/src/modules/training/presentation/http/dto/create-training-plan.response.dto.ts",
          "hash": "2677830895961480438"
        },
        {
          "file": "apps/api/src/modules/training/presentation/http/dto/get-my-training-plan.response.dto.ts",
          "hash": "11623135768168531164"
        },
        {
          "file": "apps/api/src/modules/training/presentation/http/training.controller.spec.ts",
          "hash": "18369200173164555365"
        },
        {
          "file": "apps/api/src/modules/training/presentation/http/training.controller.ts",
          "hash": "1483174121873170983"
        },
        {
          "file": "apps/api/src/modules/training/training.module.ts",
          "hash": "7740463895863647873"
        },
        {
          "file": "apps/api/src/modules/users/application/use-cases/create-user-profile/create-user-profile.errors.ts",
          "hash": "7387453205053194975"
        },
        {
          "file": "apps/api/src/modules/users/application/use-cases/create-user-profile/create-user-profile.input.ts",
          "hash": "10704960277242454877"
        },
        {
          "file": "apps/api/src/modules/users/application/use-cases/create-user-profile/create-user-profile.output.ts",
          "hash": "3528358576147737977"
        },
        {
          "file": "apps/api/src/modules/users/application/use-cases/create-user-profile/create-user-profile.use-case.spec.ts",
          "hash": "5497078835498345055"
        },
        {
          "file": "apps/api/src/modules/users/application/use-cases/create-user-profile/create-user-profile.use-case.ts",
          "hash": "3988306005840600955"
        },
        {
          "file": "apps/api/src/modules/users/domain/entities/user-profile.entity.ts",
          "hash": "5300484514136574351"
        },
        {
          "file": "apps/api/src/modules/users/domain/repositories/user-profile.repository.ts",
          "hash": "3901530595350309984"
        },
        {
          "file": "apps/api/src/modules/users/infrastructure/mongoose/mongoose-user-profile.repository.ts",
          "hash": "5049057884711470118"
        },
        {
          "file": "apps/api/src/modules/users/infrastructure/mongoose/user-profile.schema.ts",
          "hash": "10252845787923812258"
        },
        {
          "file": "apps/api/src/modules/users/presentation/http/dto/create-user-profile.request.dto.ts",
          "hash": "859500356275675084"
        },
        {
          "file": "apps/api/src/modules/users/presentation/http/dto/create-user-profile.response.dto.ts",
          "hash": "13818994321875893842"
        },
        {
          "file": "apps/api/src/modules/users/presentation/http/guards/auth-session.guard.ts",
          "hash": "5100777968548150284"
        },
        {
          "file": "apps/api/src/modules/users/presentation/http/users.controller.spec.ts",
          "hash": "10621003375166983747"
        },
        {
          "file": "apps/api/src/modules/users/presentation/http/users.controller.ts",
          "hash": "2390732063409182573"
        },
        {
          "file": "apps/api/src/modules/users/users.module.ts",
          "hash": "3579930813713474456"
        },
        {
          "file": "apps/api/test/e2e/auth-login.e2e-spec.ts",
          "hash": "13761328806946751232"
        },
        {
          "file": "apps/api/test/e2e/auth-me.e2e-spec.ts",
          "hash": "12942736572809842735"
        },
        {
          "file": "apps/api/test/e2e/auth-register.e2e-spec.ts",
          "hash": "12882177529267591324"
        },
        {
          "file": "apps/api/test/e2e/dashboard-home.e2e-spec.ts",
          "hash": "13543784800719466912"
        },
        {
          "file": "apps/api/test/e2e/fitness-create-profile.e2e-spec.ts",
          "hash": "4302530360887219450"
        },
        {
          "file": "apps/api/test/e2e/fitness-get-my-profile.e2e-spec.ts",
          "hash": "8186039287244475384"
        },
        {
          "file": "apps/api/test/e2e/progress-log-workout.e2e-spec.ts",
          "hash": "17986681592624224605"
        },
        {
          "file": "apps/api/test/e2e/progress-summary.e2e-spec.ts",
          "hash": "13507460428883036608"
        },
        {
          "file": "apps/api/test/e2e/training-create-plan.e2e-spec.ts",
          "hash": "2167069610591505950"
        },
        {
          "file": "apps/api/test/e2e/training-get-my-plan.e2e-spec.ts",
          "hash": "15555720446231943013"
        },
        {
          "file": "apps/api/test/e2e/users-create-profile.e2e-spec.ts",
          "hash": "3933642197887589669"
        },
        {
          "file": "apps/api/tsconfig.build.json",
          "hash": "11167229604194767375"
        },
        {
          "file": "apps/api/tsconfig.json",
          "hash": "9842667826211607920"
        },
        {
          "file": "apps/api/tsconfig.spec.json",
          "hash": "4294382763465427350"
        }
      ],
      "mobile": [
        {
          "file": "apps/mobile/App.tsx",
          "hash": "5219479188379596161"
        },
        {
          "file": "apps/mobile/README.md",
          "hash": "9084257131199634169"
        },
        {
          "file": "apps/mobile/app.json",
          "hash": "5418729452844367834"
        },
        {
          "file": "apps/mobile/babel.config.js",
          "hash": "11006099677513299819"
        },
        {
          "file": "apps/mobile/package.json",
          "hash": "1154524279180723725",
          "deps": [
            "npm:@babel/core",
            "npm:babel-preset-expo",
            "api-client",
            "types",
            "npm:@react-native-async-storage/async-storage@2.2.0",
            "npm:@react-navigation/native",
            "npm:@react-navigation/native-stack",
            "npm:@types/react",
            "npm:expo",
            "npm:react@19.2.0",
            "npm:react-native@0.83.6",
            "npm:react-native-safe-area-context@5.6.2",
            "npm:react-native-screens@4.23.0"
          ]
        },
        {
          "file": "apps/mobile/project.json",
          "hash": "18126538944526985039"
        },
        {
          "file": "apps/mobile/src/api/.gitkeep",
          "hash": "4055606894390288348"
        },
        {
          "file": "apps/mobile/src/api/client.ts",
          "hash": "343430817546554969"
        },
        {
          "file": "apps/mobile/src/auth/.gitkeep",
          "hash": "4055606894390288348"
        },
        {
          "file": "apps/mobile/src/auth/auth-provider.tsx",
          "hash": "13972088724183143561"
        },
        {
          "file": "apps/mobile/src/navigation/.gitkeep",
          "hash": "4055606894390288348"
        },
        {
          "file": "apps/mobile/src/navigation/app-navigator.tsx",
          "hash": "1635332114550845136"
        },
        {
          "file": "apps/mobile/src/screens/.gitkeep",
          "hash": "4055606894390288348"
        },
        {
          "file": "apps/mobile/src/screens/dashboard-screen.tsx",
          "hash": "8478357132432434665"
        },
        {
          "file": "apps/mobile/src/screens/login-screen.tsx",
          "hash": "6270863881308011562"
        },
        {
          "file": "apps/mobile/src/storage/.gitkeep",
          "hash": "4055606894390288348"
        },
        {
          "file": "apps/mobile/src/storage/token-storage.ts",
          "hash": "13669147090662883850"
        },
        {
          "file": "apps/mobile/tsconfig.json",
          "hash": "18316940084139775746"
        }
      ],
      "types": [
        {
          "file": "packages/types/package.json",
          "hash": "14910421113527804433"
        },
        {
          "file": "packages/types/project.json",
          "hash": "12293422779806322355"
        },
        {
          "file": "packages/types/src/auth/index.d.ts",
          "hash": "6290763173578397864"
        },
        {
          "file": "packages/types/src/auth/index.ts",
          "hash": "11098303769977928703"
        },
        {
          "file": "packages/types/src/dashboard/index.d.ts",
          "hash": "7222071794431369505"
        },
        {
          "file": "packages/types/src/dashboard/index.ts",
          "hash": "15420358258620660708"
        },
        {
          "file": "packages/types/src/fitness/index.d.ts",
          "hash": "15576878795257188584"
        },
        {
          "file": "packages/types/src/fitness/index.ts",
          "hash": "14540101652959229675"
        },
        {
          "file": "packages/types/src/index.d.ts",
          "hash": "12487252914168817901"
        },
        {
          "file": "packages/types/src/index.ts",
          "hash": "12487252914168817901"
        },
        {
          "file": "packages/types/src/progress/index.d.ts",
          "hash": "12449944844111274466"
        },
        {
          "file": "packages/types/src/progress/index.ts",
          "hash": "8911120045106817146"
        },
        {
          "file": "packages/types/src/training/index.d.ts",
          "hash": "14616060580392348050"
        },
        {
          "file": "packages/types/src/training/index.ts",
          "hash": "3396610573548139904"
        },
        {
          "file": "packages/types/src/users/index.d.ts",
          "hash": "4595979742548113990"
        },
        {
          "file": "packages/types/src/users/index.ts",
          "hash": "4595979742548113990"
        },
        {
          "file": "packages/types/tsconfig.json",
          "hash": "18083593526934328812"
        }
      ]
    }
  },
  "externalNodesHash": "11327160320620338550"
}